[
    {
        "id": "d8aabd0728ee42d54bbbbbea1998ced0e804a17e98365fbc381b2767c31cb58e",
        "team_1": "FC Liefering",
        "team_2": "Austria Lustenau",
        "1": "1.47",
        "X": "4.40",
        "2": "5.70",
        "ou_param": "3.5",
        "over": "2.10",
        "under": "1.65",
        "h_1": "2.15",
        "h_X": "3.90",
        "h_2": "2.45",
        "ha_param": "0:1"
    },
    {
        "id": "a45324268b273e6c54f364232c5f17c5ff484c70ea4b1f906e8b023a9d99fa15",
        "team_1": "FK Austria Wien II",
        "team_2": "BW Linz",
        "1": "2.90",
        "X": "3.80",
        "2": "2.10",
        "ou_param": "2.5",
        "over": "1.55",
        "under": "2.30",
        "h_1": "6.20",
        "h_X": "5.20",
        "h_2": "1.28",
        "ha_param": "0:1"
    },
    {
        "id": "e00a0e282b5e20e988e17c3bdf214e2ff87ec9731fd3fb802b2917d77daae77e",
        "team_1": "SV Lafnitz",
        "team_2": "FC Juniors OO",
        "1": "1.80",
        "X": "3.40",
        "2": "4.30",
        "ou_param": "2.5",
        "over": "1.70",
        "under": "2.05",
        "h_1": "2.90",
        "h_X": "3.80",
        "h_2": "1.90",
        "ha_param": "0:1"
    },
    {
        "id": "603ec50dd15e41976b99a20e1ef671637b5d6e056045e113471db42d8d9faa4a",
        "team_1": "Sk Rapid Vienna II",
        "team_2": "SKU Amstetten",
        "1": "3.30",
        "X": "3.90",
        "2": "1.90",
        "ou_param": "2.5",
        "over": "1.55",
        "under": "2.30",
        "h_1": "8.00",
        "h_X": "5.70",
        "h_2": "1.20",
        "ha_param": "0:1"
    },
    {
        "id": "a13f2a4ec9e4365d6d23935d6574d0d206aa45d83398f175012c9af88cd14ab5",
        "team_1": "Wacker Innsbruck",
        "team_2": "SK Vorwarts Steyr",
        "1": "1.57",
        "X": "3.90",
        "2": "5.20",
        "ou_param": "2.5",
        "over": "1.52",
        "under": "2.35",
        "h_1": "2.60",
        "h_X": "3.80",
        "h_2": "2.05",
        "ha_param": "0:1"
    },
    {
        "id": "3bf7bf98065b28fcf8b370ebc7ae7a91a524003fb1c173ca79bceef3b8fef88f",
        "team_1": "FC Dornbirn",
        "team_2": "SV Kapfenberg",
        "1": "2.40",
        "X": "3.50",
        "2": "2.65",
        "ou_param": "2.5",
        "over": "1.62",
        "under": "2.15",
        "h_1": "4.00",
        "h_X": "4.40",
        "h_2": "1.52",
        "ha_param": "0:1"
    },
    {
        "id": "95415466b48498f5d943372fc882e47eb53c88f97895a23a70df477cb5d26323",
        "team_1": "SV Horn",
        "team_2": "Austria Klagenfurt",
        "1": "4.20",
        "X": "3.60",
        "2": "1.75",
        "ou_param": "3.5",
        "over": "2.15",
        "under": "1.62",
        "h_1": "5.80",
        "h_X": "6.20",
        "h_2": "1.25",
        "ha_param": "0:1"
    },
    {
        "id": "6adc0092342191c30af0d502746d6ed46c1c165514a20de5fd3648f611cfa4ec",
        "team_1": "Liebherr GAK",
        "team_2": "FAC Team fur Vienna",
        "1": "2.15",
        "X": "3.50",
        "2": "3.00",
        "ou_param": "2.5",
        "over": "1.60",
        "under": "2.20",
        "h_1": "3.40",
        "h_X": "4.20",
        "h_2": "1.67",
        "ha_param": "0:1"
    }
]